string_mcp-0.1.0.dist-info/licenses/LICENSE
stringmcp/__init__.py
stringmcp/main.py
string_mcp-0.1.0.dist-info/METADATA
string_mcp-0.1.0.dist-info/WHEEL
string_mcp-0.1.0.dist-info/entry_points.txt
string_mcp-0.1.0.dist-info/top_level.txt
string_mcp-0.1.0.dist-info/RECORD
