Metadata-Version: 2.4
Name: string-mcp
Version: 0.1.0
Summary: STRING-DB API MCP Bridge - A comprehensive interface for interacting with the STRING database API
Author-email: MCPmed Contributors <matthias.flotho@ccb.uni-saarland.de>
License: MIT
Project-URL: Homepage, https://github.com/medmcp/STRINGmcp
Project-URL: Repository, https://github.com/medmcp/STRINGmcp
Project-URL: Documentation, https://github.com/medmcp/STRINGmcp#readme
Project-URL: Issues, https://github.com/medmcp/STRINGmcp/issues
Classifier: Development Status :: 3 - Alpha
Classifier: Intended Audience :: Science/Research
Classifier: License :: OSI Approved :: MIT License
Classifier: Programming Language :: Python :: 3
Classifier: Programming Language :: Python :: 3.8
Classifier: Programming Language :: Python :: 3.9
Classifier: Programming Language :: Python :: 3.10
Classifier: Programming Language :: Python :: 3.11
Classifier: Programming Language :: Python :: 3.12
Classifier: Topic :: Scientific/Engineering :: Bio-Informatics
Requires-Python: >=3.8
License-File: LICENSE
Requires-Dist: requests>=2.25.0
Provides-Extra: dev
Requires-Dist: pytest>=6.0; extra == "dev"
Requires-Dist: pytest-cov>=2.0; extra == "dev"
Requires-Dist: black>=21.0; extra == "dev"
Requires-Dist: flake8>=3.8; extra == "dev"
Requires-Dist: mypy>=0.800; extra == "dev"
Dynamic: license-file
